{
    "success": true,
    "message": "Island Results!",
    "islands": [
        {
            "name": "Silver",
            "background": null,
            "fruit": "apple",
            "turnipPrice": 95,
            "maxQueue": 50,
            "turnipCode": "c34bdec2",
            "hemisphere": "north",
            "watchlist": 0,
            "fee": 0,
            "islander": "daisy",
            "category": "turnips",
            "islandTime": "2020-05-06T17:28:03.000Z",
            "creationTime": "2020-05-06 15:16:10",
            "description": "I trapped Daisy by the beach. \nI'm in the all gray with fedora, tips welcome not required. \nIf you want to pick some fruit, ask. \nMulti trips you need to re-queue.",
            "queued": "18/50",
            "patreon": 0,
            "discordOnly": 1,
            "patreonOnly": 0,
            "messageID": "707685965539442825",
            "thumbsupt": 0,
            "thumbsdown": 0,
            "heart": 0,
            "poop": 0,
            "clown": 0,
            "islandScore": null
        },
        {
            "name": "Sakura",
            "background": "nups",
            "fruit": "pear",
            "turnipPrice": 106,
            "maxQueue": 25,
            "turnipCode": "56aaa44e",
            "hemisphere": "north",
            "watchlist": 0,
            "fee": 0,
            "islander": "daisy",
            "category": "turnips",
            "islandTime": "2020-05-06T17:34:09.000Z",
            "creationTime": "2020-05-06 13:55:05",
            "description": "No enter Fee . Tips are appreciated NMT ,Golden Nugget, Bells or what ever u want give me. Multi trips okay. please's Leave by airport!!! I am Tried getting disconnected errors from others and going look for Daisy and Pushing her around Then Gate her off! My Discord Server if you Get Disconnected or updates 6ERpj2X ",
            "queued": "14/25",
            "patreon": 2,
            "discordOnly": 0,
            "patreonOnly": 0,
            "messageID": "707666555445444820",
            "thumbsupt": 1,
            "thumbsdown": 2,
            "heart": 0,
            "poop": -1,
            "clown": 0,
            "islandScore": -16
        },
        {
            "name": "mionara",
            "background": null,
            "fruit": "pear",
            "turnipPrice": 96,
            "maxQueue": 30,
            "turnipCode": "47d1556c",
            "hemisphere": "north",
            "watchlist": 0,
            "fee": 0,
            "islander": "daisy",
            "category": "turnips",
            "islandTime": "2020-05-17T09:01:35.000Z",
            "creationTime": "2020-05-06 16:34:29",
            "description": "Hey! Daisy selling for 96 so you're gonna have to find her around the island! Please don't run over my flowers but you're welcome to take fruit and explore!! Tips of 99k bags would be highly appreciated but not required!",
            "queued": "14/30",
            "patreon": 0,
            "discordOnly": 0,
            "patreonOnly": 0,
            "messageID": "707704352772456483",
            "thumbsupt": 0,
            "thumbsdown": 0,
            "heart": 0,
            "poop": 0,
            "clown": 0,
            "islandScore": null
        },
        {
            "name": "Lelö",
            "background": null,
            "fruit": "apple",
            "turnipPrice": 106,
            "maxQueue": 30,
            "turnipCode": "5eed8fb9",
            "hemisphere": "north",
            "watchlist": 0,
            "fee": 0,
            "islander": "daisy",
            "category": "turnips",
            "islandTime": "2020-05-03T11:22:58.000Z",
            "creationTime": "2020-05-06 13:50:40",
            "description": "DAISY MAE IS ON MY ISLAND!\nSELLING TURNIPS FOR 106!\nDonations would be appreciated \nLooking for clothes and furniture \nDROP OFF AT THE LEFT BEACH SIDE (my house)\nI have a  DROP ONE and TAKE ONE on my island\nFEEL FREE TO GO TO  MY twitter and enter my 1 million giveaway!!! \nIm wearing a face mask and pink hair @  the gate",
            "queued": "7/30",
            "patreon": 0,
            "discordOnly": 0,
            "patreonOnly": 0,
            "messageID": "707666251799068803",
            "thumbsupt": 0,
            "thumbsdown": 1,
            "heart": 0,
            "poop": 0,
            "clown": 1,
            "islandScore": null
        },
        {
            "name": "Avalon",
            "background": null,
            "fruit": "peach",
            "turnipPrice": 91,
            "maxQueue": 100,
            "turnipCode": "bbb1b838",
            "hemisphere": "north",
            "watchlist": 0,
            "fee": 0,
            "islander": "daisy",
            "category": "turnips",
            "islandTime": "2020-05-03T08:10:55.000Z",
            "creationTime": "2020-05-06 16:06:18",
            "description": "Turnips selling for 91 bells. Dairy is trapped near the airport. Tips appreciated. Please leave by the airport.",
            "queued": "35/100",
            "patreon": 0,
            "discordOnly": 0,
            "patreonOnly": 0,
            "messageID": "707687228536520796",
            "thumbsupt": 0,
            "thumbsdown": 0,
            "heart": 0,
            "poop": 0,
            "clown": 0,
            "islandScore": null
        },
        {
            "name": "FoolsVille",
            "background": null,
            "fruit": "apple",
            "turnipPrice": 389,
            "maxQueue": 25,
            "turnipCode": "15dcadcf",
            "hemisphere": "north",
            "watchlist": 0,
            "fee": 0,
            "islander": "daisy",
            "category": "turnips",
            "islandTime": "2020-05-06T17:18:58.000Z",
            "creationTime": "2020-05-06 16:32:44",
            "description": "",
            "queued": "0/25",
            "patreon": 0,
            "discordOnly": 0,
            "patreonOnly": 0,
            "messageID": "707706441359818755",
            "thumbsupt": 0,
            "thumbsdown": 0,
            "heart": 0,
            "poop": 0,
            "clown": 0,
            "islandScore": null
        },
        {
            "name": "Endor",
            "background": null,
            "fruit": "orange",
            "turnipPrice": 0,
            "maxQueue": 50,
            "turnipCode": "e19dc336",
            "hemisphere": "north",
            "watchlist": 0,
            "fee": 0,
            "islander": "daisy",
            "category": "turnips",
            "islandTime": "2020-05-06T17:33:36.000Z",
            "creationTime": "2020-05-06 16:23:11",
            "description": "Daisy is selling for 93 bells! she is trapped at the airport. No entry fee tips are nice because im very in debt :)",
            "queued": "25/50",
            "patreon": 0,
            "discordOnly": 0,
            "patreonOnly": 0,
            "messageID": "707704038694846467",
            "thumbsupt": 0,
            "thumbsdown": 0,
            "heart": 0,
            "poop": 0,
            "clown": 0,
            "islandScore": null
        },
        {
            "name": "Beauclair",
            "background": null,
            "fruit": "orange",
            "turnipPrice": 96,
            "maxQueue": 180,
            "turnipCode": "9cf956e9",
            "hemisphere": "north",
            "watchlist": 0,
            "fee": 0,
            "islander": "daisy",
            "category": "turnips",
            "islandTime": "2020-05-24T10:22:10.000Z",
            "creationTime": "2020-05-06 16:34:01",
            "description": "daisy trapped right outside of the airport, no fee tips are appreciated. please leave by airport so it doesnt reset daisy. ill be running around my island and its blocked off by the fence so just buy from daisy and let the next person come though thank you.",
            "queued": "17/180",
            "patreon": 0,
            "discordOnly": 0,
            "patreonOnly": 0,
            "messageID": "707706026526244926",
            "thumbsupt": 0,
            "thumbsdown": 0,
            "heart": 0,
            "poop": 0,
            "clown": 0,
            "islandScore": null
        }
    ],
    "$$time": 44489075.927726746
}